[["loop_queue1", [{
                "exits": [{
                        "_DEFAULT_SOURCE_ANCHOR": "s4",
                        "type": "default",
                        "sourceEndPoints": [{
                                "endPointType": "s2",
                                "params": [0, 0.5, -1, 0, 0, 0, "left"]
                            }, {
                                "endPointType": "s3",
                                "params": [1, 0.5, 1, 0, 0, 0, "right"]
                            }
                        ],
                        "text": "default",
                        "moduleId": "loop_queue1_entrypointloop",
                        "id": "-1249665658_1544803905_loop_queue1_entrypointloop_default",
                        "next": {
                            "targetId": "audio_loop_queue1_1",
                            "target": "1",
                            "source": "s4"
                        },
                        "_isVisible": false
                    }
                ],
                "tabs": [["Basic", {
                            "tabName": "Basic",
                            "moduleType": "loop-entrypoint",
                            "propertyValues": [["name", "loop_queue1"], ["count", "forever"]],
                            "moduleId": "loop_queue1",
                            "moduleName": "loop_queue1",
                            "isSelected": true
                        }
                    ], ["Advanced", {
                            "tabName": "Advanced",
                            "moduleType": "loop-entrypoint",
                            "propertyValues": [["id", "loop_queue1_entrypointloop"]],
                            "moduleId": "loop_queue1",
                            "moduleName": "loop_queue1",
                            "isSelected": false
                        }
                    ]],
                "isValid": true
            }, {
                "exits": [{
                        "_DEFAULT_SOURCE_ANCHOR": "s4",
                        "type": "default",
                        "sourceEndPoints": [{
                                "endPointType": "s2",
                                "params": [0, 0.5, -1, 0, 0, 0, "left"]
                            }, {
                                "endPointType": "s3",
                                "params": [1, 0.5, 1, 0, 0, 0, "right"]
                            }
                        ],
                        "text": "default",
                        "exitDefaultTarget": "queue1_entertainer_end",
                        "moduleId": "audio_loop_queue1_1",
                        "id": "-1217435772_1544803905_audio_loop_queue1_1_default",
                        "next": {
                            "targetId": "audio1",
                            "target": "2",
                            "source": "s3"
                        },
                        "_isVisible": false
                    }
                ],
                "tabs": [["Basic", {
                            "tabName": "Basic",
                            "moduleType": "audio",
                            "propertyValues": [["name", "Ringing_30"], ["src", "ringing_tone"]],
                            "moduleId": "audio_loop_queue1_1",
                            "moduleName": "Ringing_30",
                            "isSelected": true
                        }
                    ], ["Advanced", {
                            "tabName": "Advanced",
                            "moduleType": "audio",
                            "propertyValues": [["format", null], ["timeout", "30s"], ["conid", ""], ["ct_label", null], ["cc_label", "Ringing_30"]],
                            "moduleId": "audio_loop_queue1_1",
                            "moduleName": "Ringing_30",
                            "isSelected": false
                        }
                    ]],
                "isValid": true
            }, {
                "exits": [{
                        "_DEFAULT_SOURCE_ANCHOR": "s4",
                        "type": "default",
                        "sourceEndPoints": [{
                                "endPointType": "s2",
                                "params": [0, 0.5, -1, 0, 0, 0, "left"]
                            }, {
                                "endPointType": "s3",
                                "params": [1, 0.5, 1, 0, 0, 0, "right"]
                            }
                        ],
                        "text": "default",
                        "exitDefaultTarget": "queue1_entertainer_end",
                        "moduleId": "audio1",
                        "id": "-1406804197_1544803905_audio1_default",
                        "next": {
                            "targetId": "loop_queue1_exitpointloop",
                            "target": "2",
                            "source": "s3"
                        },
                        "_isVisible": false
                    }
                ],
                "tabs": [["Basic", {
                            "tabName": "Basic",
                            "moduleType": "audio",
                            "propertyValues": [["name", "Busy"], ["src", "/500187/ControlAudio/Busy.wav"]],
                            "moduleId": "audio1",
                            "moduleName": "Busy",
                            "isSelected": true
                        }
                    ], ["Advanced", {
                            "tabName": "Advanced",
                            "moduleType": "audio",
                            "propertyValues": [["format", null], ["timeout", null], ["conid", ""], ["ct_label", null], ["cc_label", "Busy"]],
                            "moduleId": "audio1",
                            "moduleName": "Busy",
                            "isSelected": false
                        }
                    ]],
                "isValid": true
            }, {
                "exits": [],
                "tabs": [["Basic", {
                            "tabName": "Basic",
                            "moduleType": "loop-exitpoint",
                            "propertyValues": [],
                            "moduleId": "loop_queue1",
                            "moduleName": "loop_queue1",
                            "isSelected": true
                        }
                    ], ["Advanced", {
                            "tabName": "Advanced",
                            "moduleType": "loop-exitpoint",
                            "propertyValues": [["id", "loop_queue1_exitpointloop"]],
                            "moduleId": "loop_queue1",
                            "moduleName": "loop_queue1",
                            "isSelected": false
                        }
                    ]],
                "isValid": true
            }
        ]], ["queue1", [{
                "exits": [{
                        "_DEFAULT_SOURCE_ANCHOR": "s4",
                        "type": "default",
                        "sourceEndPoints": [{
                                "endPointType": "s2",
                                "params": [0, 0.5, -1, 0, 0, 0, "left"]
                            }, {
                                "endPointType": "s3",
                                "params": [1, 0.5, 1, 0, 0, 0, "right"]
                            }
                        ],
                        "text": "default",
                        "moduleId": "queue1_entrypointqueue",
                        "id": "-440189324_1544803905_queue1_entrypointqueue_default",
                        "next": {
                            "targetId": "audio7",
                            "target": "2",
                            "source": "s4"
                        },
                        "_isVisible": false
                    }
                ],
                "tabs": [["Basic", {
                            "tabName": "Basic",
                            "moduleType": "queue-entrypoint",
                            "propertyValues": [["name", "Основна опашка"], ["count", null]],
                            "moduleId": "queue1",
                            "moduleName": "Основна опашка",
                            "isSelected": true
                        }
                    ], ["Advanced", {
                            "tabName": "Advanced",
                            "moduleType": "queue-entrypoint",
                            "propertyValues": [["id", "queue1_entrypointqueue"]],
                            "moduleId": "queue1",
                            "moduleName": "Основна опашка",
                            "isSelected": false
                        }
                    ]],
                "isValid": true
            }, {
                "exits": [{
                        "_DEFAULT_SOURCE_ANCHOR": "s4",
                        "type": "default",
                        "sourceEndPoints": [{
                                "endPointType": "s2",
                                "params": [0, 0.5, -1, 0, 0, 0, "left"]
                            }, {
                                "endPointType": "s3",
                                "params": [1, 0.5, 1, 0, 0, 0, "right"]
                            }
                        ],
                        "text": "default",
                        "exitDefaultTarget": "queue1_entertainer_end",
                        "moduleId": "audio7",
                        "id": "-1406804191_1544803905_audio7_default",
                        "next": {
                            "targetId": "audio8",
                            "target": "2",
                            "source": "s3"
                        },
                        "_isVisible": false
                    }
                ],
                "tabs": [["Basic", {
                            "tabName": "Basic",
                            "moduleType": "audio",
                            "propertyValues": [["name", "Ring_20"], ["src", "ringing_tone"]],
                            "moduleId": "audio7",
                            "moduleName": "Ring_20",
                            "isSelected": true
                        }
                    ], ["Advanced", {
                            "tabName": "Advanced",
                            "moduleType": "audio",
                            "propertyValues": [["format", null], ["timeout", "20s"], ["conid", ""], ["ct_label", null], ["cc_label", "Ring_20"]],
                            "moduleId": "audio7",
                            "moduleName": "Ring_20",
                            "isSelected": false
                        }
                    ]],
                "isValid": true
            }, {
                "exits": [{
                        "_DEFAULT_SOURCE_ANCHOR": "s4",
                        "type": "default",
                        "sourceEndPoints": [{
                                "endPointType": "s2",
                                "params": [0, 0.5, -1, 0, 0, 0, "left"]
                            }, {
                                "endPointType": "s3",
                                "params": [1, 0.5, 1, 0, 0, 0, "right"]
                            }
                        ],
                        "text": "default",
                        "exitDefaultTarget": "queue1_entertainer_end",
                        "moduleId": "loop_queue1",
                        "id": "-513327301_1544803905_loop_queue1_default",
                        "next": {
                            "targetId": "queue1_exitpointqueue",
                            "target": "2",
                            "source": "s3"
                        },
                        "_isVisible": true
                    }
                ],
                "tabs": [["Basic", {
                            "tabName": "Basic",
                            "moduleType": "loop",
                            "propertyValues": [["name", "loop_queue1"]],
                            "moduleId": "loop_queue1",
                            "moduleName": "loop_queue1",
                            "isSelected": true
                        }
                    ], ["Advanced", {
                            "tabName": "Advanced",
                            "moduleType": "loop",
                            "propertyValues": [],
                            "moduleId": "loop_queue1",
                            "moduleName": "loop_queue1",
                            "isSelected": false
                        }
                    ]],
                "isValid": true
            }, {
                "exits": [{
                        "_DEFAULT_SOURCE_ANCHOR": "s4",
                        "type": "default",
                        "sourceEndPoints": [{
                                "endPointType": "s2",
                                "params": [0, 0.5, -1, 0, 0, 0, "left"]
                            }, {
                                "endPointType": "s3",
                                "params": [1, 0.5, 1, 0, 0, 0, "right"]
                            }
                        ],
                        "text": "default",
                        "exitDefaultTarget": "queue1_entertainer_end",
                        "moduleId": "audio8",
                        "id": "-1406804190_1544803905_audio8_default",
                        "next": {
                            "targetId": "loop_queue1",
                            "target": "2",
                            "source": "s3"
                        },
                        "_isVisible": false
                    }
                ],
                "tabs": [["Basic", {
                            "tabName": "Basic",
                            "moduleType": "audio",
                            "propertyValues": [["name", "Busy_"], ["src", "/500187/ControlAudio/Busy.wav"]],
                            "moduleId": "audio8",
                            "moduleName": "Busy_",
                            "isSelected": true
                        }
                    ], ["Advanced", {
                            "tabName": "Advanced",
                            "moduleType": "audio",
                            "propertyValues": [["format", null], ["timeout", null], ["conid", ""], ["ct_label", null], ["cc_label", "Busy_"]],
                            "moduleId": "audio8",
                            "moduleName": "Busy_",
                            "isSelected": false
                        }
                    ]],
                "isValid": true
            }, {
                "exits": [],
                "tabs": [["Basic", {
                            "tabName": "Basic",
                            "moduleType": "queue-exitpoint",
                            "propertyValues": [],
                            "moduleId": "queue1",
                            "moduleName": "Основна опашка",
                            "isSelected": true
                        }
                    ], ["Advanced", {
                            "tabName": "Advanced",
                            "moduleType": "queue-exitpoint",
                            "propertyValues": [["id", "queue1_exitpointqueue"]],
                            "moduleId": "queue1",
                            "moduleName": "Основна опашка",
                            "isSelected": false
                        }
                    ]],
                "isValid": true
            }
        ]], ["loop1", [{
                "exits": [{
                        "_DEFAULT_SOURCE_ANCHOR": "s4",
                        "type": "default",
                        "sourceEndPoints": [{
                                "endPointType": "s2",
                                "params": [0, 0.5, -1, 0, 0, 0, "left"]
                            }, {
                                "endPointType": "s3",
                                "params": [1, 0.5, 1, 0, 0, 0, "right"]
                            }
                        ],
                        "text": "default",
                        "moduleId": "loop1_entrypointloop",
                        "id": "657920116_1544803905_loop1_entrypointloop_default",
                        "next": {
                            "targetId": "audio4",
                            "target": "1",
                            "source": "s4"
                        },
                        "_isVisible": false
                    }
                ],
                "tabs": [["Basic", {
                            "tabName": "Basic",
                            "moduleType": "loop-entrypoint",
                            "propertyValues": [["name", "loop_queue2 copy (0)"], ["count", "forever"]],
                            "moduleId": "loop1",
                            "moduleName": "loop_queue2 copy (0)",
                            "isSelected": true
                        }
                    ], ["Advanced", {
                            "tabName": "Advanced",
                            "moduleType": "loop-entrypoint",
                            "propertyValues": [["id", "loop1_entrypointloop"]],
                            "moduleId": "loop1",
                            "moduleName": "loop_queue2 copy (0)",
                            "isSelected": false
                        }
                    ]],
                "isValid": true
            }, {
                "exits": [{
                        "_DEFAULT_SOURCE_ANCHOR": "s4",
                        "type": "default",
                        "sourceEndPoints": [{
                                "endPointType": "s2",
                                "params": [0, 0.5, -1, 0, 0, 0, "left"]
                            }, {
                                "endPointType": "s3",
                                "params": [1, 0.5, 1, 0, 0, 0, "right"]
                            }
                        ],
                        "text": "default",
                        "exitDefaultTarget": "queue3_entertainer_end",
                        "moduleId": "audio4",
                        "id": "-1406804194_1544803905_audio4_default",
                        "next": {
                            "targetId": "audio9",
                            "target": "2",
                            "source": "s3"
                        },
                        "_isVisible": false
                    }
                ],
                "tabs": [["Basic", {
                            "tabName": "Basic",
                            "moduleType": "audio",
                            "propertyValues": [["name", "non working hours"], ["src", "/500187/ControlAudio/Non working hours.wav"]],
                            "moduleId": "audio4",
                            "moduleName": "non working hours",
                            "isSelected": true
                        }
                    ], ["Advanced", {
                            "tabName": "Advanced",
                            "moduleType": "audio",
                            "propertyValues": [["format", null], ["timeout", null], ["conid", ""], ["ct_label", null], ["cc_label", "non working hours"]],
                            "moduleId": "audio4",
                            "moduleName": "non working hours",
                            "isSelected": false
                        }
                    ]],
                "isValid": true
            }, {
                "exits": [{
                        "_DEFAULT_SOURCE_ANCHOR": "s4",
                        "type": "default",
                        "sourceEndPoints": [{
                                "endPointType": "s2",
                                "params": [0, 0.5, -1, 0, 0, 0, "left"]
                            }, {
                                "endPointType": "s3",
                                "params": [1, 0.5, 1, 0, 0, 0, "right"]
                            }
                        ],
                        "text": "default",
                        "exitDefaultTarget": "queue3_entertainer_end",
                        "moduleId": "audio9",
                        "id": "-1406804189_1544803905_audio9_default",
                        "next": {
                            "targetId": "loop1_exitpointloop",
                            "target": "2",
                            "source": "s3"
                        },
                        "_isVisible": false
                    }
                ],
                "tabs": [["Basic", {
                            "tabName": "Basic",
                            "moduleType": "audio",
                            "propertyValues": [["name", "ringing"], ["src", "ringing_tone"]],
                            "moduleId": "audio9",
                            "moduleName": "ringing",
                            "isSelected": true
                        }
                    ], ["Advanced", {
                            "tabName": "Advanced",
                            "moduleType": "audio",
                            "propertyValues": [["format", null], ["timeout", "300s"], ["conid", ""], ["ct_label", null], ["cc_label", "ringing"]],
                            "moduleId": "audio9",
                            "moduleName": "ringing",
                            "isSelected": false
                        }
                    ]],
                "isValid": true
            }, {
                "exits": [],
                "tabs": [["Basic", {
                            "tabName": "Basic",
                            "moduleType": "loop-exitpoint",
                            "propertyValues": [],
                            "moduleId": "loop1",
                            "moduleName": "loop_queue2 copy (0)",
                            "isSelected": true
                        }
                    ], ["Advanced", {
                            "tabName": "Advanced",
                            "moduleType": "loop-exitpoint",
                            "propertyValues": [["id", "loop1_exitpointloop"]],
                            "moduleId": "loop1",
                            "moduleName": "loop_queue2 copy (0)",
                            "isSelected": false
                        }
                    ]],
                "isValid": true
            }
        ]], ["queue3", [{
                "exits": [{
                        "_DEFAULT_SOURCE_ANCHOR": "s4",
                        "type": "default",
                        "sourceEndPoints": [{
                                "endPointType": "s2",
                                "params": [0, 0.5, -1, 0, 0, 0, "left"]
                            }, {
                                "endPointType": "s3",
                                "params": [1, 0.5, 1, 0, 0, 0, "right"]
                            }
                        ],
                        "text": "default",
                        "moduleId": "queue3_entrypointqueue",
                        "id": "-2028537226_1544803905_queue3_entrypointqueue_default",
                        "next": {
                            "targetId": "loop1",
                            "target": "1",
                            "source": "s4"
                        },
                        "_isVisible": false
                    }
                ],
                "tabs": [["Basic", {
                            "tabName": "Basic",
                            "moduleType": "queue-entrypoint",
                            "propertyValues": [["name", "Дежурен"], ["count", null]],
                            "moduleId": "queue3",
                            "moduleName": "Дежурен",
                            "isSelected": true
                        }
                    ], ["Advanced", {
                            "tabName": "Advanced",
                            "moduleType": "queue-entrypoint",
                            "propertyValues": [["id", "queue3_entrypointqueue"]],
                            "moduleId": "queue3",
                            "moduleName": "Дежурен",
                            "isSelected": false
                        }
                    ]],
                "isValid": true
            }, {
                "exits": [{
                        "_DEFAULT_SOURCE_ANCHOR": "s4",
                        "type": "default",
                        "sourceEndPoints": [{
                                "endPointType": "s2",
                                "params": [0, 0.5, -1, 0, 0, 0, "left"]
                            }, {
                                "endPointType": "s3",
                                "params": [1, 0.5, 1, 0, 0, 0, "right"]
                            }
                        ],
                        "text": "default",
                        "exitDefaultTarget": "queue3_entertainer_end",
                        "moduleId": "loop1",
                        "id": "103157261_1544803905_loop1_default",
                        "next": {
                            "targetId": "queue3_exitpointqueue",
                            "target": "1",
                            "source": "s3"
                        },
                        "_isVisible": true
                    }
                ],
                "tabs": [["Basic", {
                            "tabName": "Basic",
                            "moduleType": "loop",
                            "propertyValues": [["name", "loop_queue2 copy (0)"]],
                            "moduleId": "loop1",
                            "moduleName": "loop_queue2 copy (0)",
                            "isSelected": true
                        }
                    ], ["Advanced", {
                            "tabName": "Advanced",
                            "moduleType": "loop",
                            "propertyValues": [],
                            "moduleId": "loop1",
                            "moduleName": "loop_queue2 copy (0)",
                            "isSelected": false
                        }
                    ]],
                "isValid": true
            }, {
                "exits": [],
                "tabs": [["Basic", {
                            "tabName": "Basic",
                            "moduleType": "queue-exitpoint",
                            "propertyValues": [],
                            "moduleId": "queue3",
                            "moduleName": "Дежурен",
                            "isSelected": true
                        }
                    ], ["Advanced", {
                            "tabName": "Advanced",
                            "moduleType": "queue-exitpoint",
                            "propertyValues": [["id", "queue3_exitpointqueue"]],
                            "moduleId": "queue3",
                            "moduleName": "Дежурен",
                            "isSelected": false
                        }
                    ]],
                "isValid": true
            }
        ]], ["rootnode", [{
                "exits": [{
                        "_DEFAULT_SOURCE_ANCHOR": "s4",
                        "type": "default",
                        "sourceEndPoints": [{
                                "endPointType": "s2",
                                "params": [0, 0.5, -1, 0, 0, 0, "left"]
                            }, {
                                "endPointType": "s3",
                                "params": [1, 0.5, 1, 0, 0, 0, "right"]
                            }
                        ],
                        "text": "default",
                        "exitDefaultTarget": "terminate",
                        "moduleId": "rootnode",
                        "id": "-166072860_1544803905_rootnode_default",
                        "next": {
                            "targetId": "script1",
                            "target": "1",
                            "source": "s4"
                        },
                        "_isVisible": false
                    }
                ],
                "tabs": [["Basic", {
                            "tabName": "Basic",
                            "moduleType": "service",
                            "propertyValues": [["name", "Start module"], ["enableCallout", true]],
                            "moduleId": "rootnode",
                            "moduleName": "Start module",
                            "isSelected": true
                        }
                    ], ["Advanced", {
                            "tabName": "Advanced",
                            "moduleType": "service",
                            "propertyValues": [["hide_dtmf", null], ["immediate_answer", ""], ["trace_level", null], ["tone_detection_mode", null], ["time_to_live", null], ["initialScript", null], ["finallyScript", null]],
                            "moduleId": "rootnode",
                            "moduleName": "Start module",
                            "isSelected": false
                        }
                    ]],
                "isValid": true
            }, {
                "exits": [{
                        "_DEFAULT_SOURCE_ANCHOR": "s4",
                        "type": "default",
                        "sourceEndPoints": [{
                                "endPointType": "s2",
                                "params": [0, 0.5, -1, 0, 0, 0, "left"]
                            }, {
                                "endPointType": "s3",
                                "params": [1, 0.5, 1, 0, 0, 0, "right"]
                            }
                        ],
                        "text": "default",
                        "exitDefaultTarget": "terminate",
                        "moduleId": "script1",
                        "id": "1926514886_1544803905_script1_default",
                        "next": {
                            "targetId": "time1",
                            "target": "2",
                            "source": "s4"
                        },
                        "_isVisible": false
                    }
                ],
                "tabs": [["Basic", {
                            "tabName": "Basic",
                            "moduleType": "script",
                            "propertyValues": [["name", "LogCall"], ["script", "<mir method=\"LogCall\" timeout=\"10s\"><in variable=\"phoneNumber\" value=\"$(ciq_destination)\"/><in variable=\"xsltUri\" value=\"http://cs.prod.consorte.com/Common/MIR/LogCall/crmdb_return_v1.xslt\"/><out variable=\"result\"/><out variable=\"crmKml\"/><default><switch variable=\"result\"><case value=\"OK\"><include variable=\"crmKml\"/><assign variable=\"crmKml\" value=\"\"/></case></switch></default></mir>"]],
                            "moduleId": "script1",
                            "moduleName": "LogCall",
                            "isSelected": true
                        }
                    ], ["Advanced", {
                            "tabName": "Advanced",
                            "moduleType": "script",
                            "propertyValues": [],
                            "moduleId": "script1",
                            "moduleName": "LogCall",
                            "isSelected": false
                        }
                    ]],
                "isValid": true
            }, {
                "exits": [{
                        "name": "Отворено",
                        "type": "time",
                        "sourceEndPoints": [{
                                "endPointType": "s2",
                                "params": [0, 0.5, -1, 0, 0, 0, "left"]
                            }, {
                                "endPointType": "s3",
                                "params": [1, 0.5, 1, 0, 0, 0, "right"]
                            }
                        ],
                        "text": "Отворено",
                        "exitDefaultTarget": "terminate",
                        "moduleId": "time1",
                        "id": "110364420_1406824326_time1_Отворено",
                        "next": {
                            "targetId": "audio6",
                            "target": "2",
                            "source": "s3"
                        }
                    }, {
                        "name": "Затворено",
                        "type": "time",
                        "sourceEndPoints": [{
                                "endPointType": "s2",
                                "params": [0, 0.5, -1, 0, 0, 0, "left"]
                            }, {
                                "endPointType": "s3",
                                "params": [1, 0.5, 1, 0, 0, 0, "right"]
                            }
                        ],
                        "text": "Затворено",
                        "exitDefaultTarget": "terminate",
                        "moduleId": "time1",
                        "id": "110364420_93426763_time1_Затворено",
                        "next": {
                            "targetId": "queue3",
                            "target": "2",
                            "source": "s3"
                        }
                    }, {
                        "name": "Дежурен",
                        "type": "time",
                        "sourceEndPoints": [{
                                "endPointType": "s2",
                                "params": [0, 0.5, -1, 0, 0, 0, "left"]
                            }, {
                                "endPointType": "s3",
                                "params": [1, 0.5, 1, 0, 0, 0, "right"]
                            }
                        ],
                        "text": "Дежурен",
                        "exitDefaultTarget": "terminate",
                        "moduleId": "time1",
                        "id": "110364420_638869242_time1_Дежурен",
                        "next": {
                            "targetId": "queue3",
                            "target": "2",
                            "source": "s3"
                        }
                    }, {
                        "_DEFAULT_SOURCE_ANCHOR": "s4",
                        "type": "default",
                        "sourceEndPoints": [{
                                "endPointType": "s2",
                                "params": [0, 0.5, -1, 0, 0, 0, "left"]
                            }, {
                                "endPointType": "s3",
                                "params": [1, 0.5, 1, 0, 0, 0, "right"]
                            }
                        ],
                        "text": "default",
                        "exitDefaultTarget": "terminate",
                        "moduleId": "time1",
                        "id": "110364420_1544803905_time1_default",
                        "next": {
                            "targetId": "queue3",
                            "target": "2",
                            "source": "s3"
                        },
                        "_isVisible": true
                    }
                ],
                "tabs": [["Basic", {
                            "tabName": "Basic",
                            "moduleType": "time",
                            "propertyValues": [["id", "time1"], ["name", "Работно време"], ["src", null], ["cc_label", "Работно време"], ["kml", {
                                        "type": "element",
                                        "name": "time",
                                        "attr": {
                                            "cc_label": "Работно време",
                                            "id": "time1",
                                            "name": "Работно време"
                                        },
                                        "tags": [{
                                                "type": "element",
                                                "name": "times",
                                                "tags": [{
                                                        "type": "element",
                                                        "name": "entry",
                                                        "attr": {
                                                            "day": "weekday",
                                                            "time": "0800-1759",
                                                            "exit": "Отворено"
                                                        }
                                                    }, {
                                                        "type": "element",
                                                        "name": "entry",
                                                        "attr": {
                                                            "day": "weekday",
                                                            "time": "1800-2359",
                                                            "exit": "Дежурен"
                                                        }
                                                    }, {
                                                        "type": "element",
                                                        "name": "entry",
                                                        "attr": {
                                                            "day": "weekday",
                                                            "time": "0000-0759",
                                                            "exit": "Дежурен"
                                                        }
                                                    }, {
                                                        "type": "element",
                                                        "name": "entry",
                                                        "attr": {
                                                            "day": "weekend",
                                                            "time": "0000-2359",
                                                            "exit": "Дежурен"
                                                        }
                                                    }
                                                ]
                                            }, {
                                                "type": "element",
                                                "name": "exit",
                                                "attr": {
                                                    "name": "Отворено",
                                                    "next": "audio6",
                                                    "description": "Отворено"
                                                }
                                            }, {
                                                "type": "element",
                                                "name": "exit",
                                                "attr": {
                                                    "name": "Затворено",
                                                    "next": "queue3",
                                                    "description": "Затворено"
                                                }
                                            }, {
                                                "type": "element",
                                                "name": "exit",
                                                "attr": {
                                                    "name": "Дежурен",
                                                    "next": "queue3",
                                                    "description": "Дежурен"
                                                }
                                            }, {
                                                "type": "element",
                                                "name": "default",
                                                "attr": {
                                                    "description": "Дежурен",
                                                    "next": "queue3"
                                                }
                                            }
                                        ]
                                    }
                                ], ["isDefaultExitVisible", true], ["exitsJson", "[{\"name\":\"Отворено\",\"description\":\"Отворено\",\"isTimeEntryExit\":true},{\"name\":\"Затворено\",\"description\":\"Затворено\",\"isTimeEntryExit\":false},{\"name\":\"Дежурен\",\"description\":\"Дежурен\",\"isTimeEntryExit\":true}]"], ["timeModule", {}
                                ], ["sharedTimeModule", {}
                                ], ["moduleMode", "local"], ["srcExitsEntriesJson", ""], ["areExitsDuplicate", false]],
                            "moduleId": "time1",
                            "moduleName": "Работно време",
                            "isSelected": true
                        }
                    ], ["Opening Hours", {
                            "tabName": "Opening Hours",
                            "moduleType": "time",
                            "propertyValues": [["src", null], ["timeEntriesJson", "[{\"day\":\"weekday\",\"time\":\"0800-1759\",\"exit\":\"Отворено\"},{\"day\":\"weekday\",\"time\":\"1800-2359\",\"exit\":\"Дежурен\"},{\"day\":\"weekday\",\"time\":\"0000-0759\",\"exit\":\"Дежурен\"},{\"day\":\"weekend\",\"time\":\"0000-2359\",\"exit\":\"Дежурен\"}]"]],
                            "moduleId": "time1",
                            "moduleName": "Работно време",
                            "isSelected": false
                        }
                    ], ["Advanced", {
                            "tabName": "Advanced",
                            "moduleType": "time",
                            "propertyValues": [["ct_label", null]],
                            "moduleId": "time1",
                            "moduleName": "Работно време",
                            "isSelected": false
                        }
                    ]],
                "isValid": true
            }, {
                "exits": [{
                        "tag_name": "cancel",
                        "type": "cancel",
                        "sourceEndPoints": [{
                                "endPointType": "s2",
                                "params": [0, 0.5, -1, 0, 0, 0, "left"]
                            }, {
                                "endPointType": "s3",
                                "params": [1, 0.5, 1, 0, 0, 0, "right"]
                            }
                        ],
                        "text": "cancel",
                        "exitDefaultTarget": "terminate",
                        "moduleId": "queue1",
                        "id": "-948696768_-1367724422_queue1_cancel",
                        "next": {
                            "targetId": "terminate",
                            "target": "1",
                            "source": "s3"
                        }
                    }
                ],
                "tabs": [["Basic", {
                            "tabName": "Basic",
                            "moduleType": "queue",
                            "propertyValues": [["name", "Основна опашка"], ["queue_key", "q_phоne"], ["hascustomentertainer", "false"], ["exitsJson", "[{\"type\":\"cancel\",\"text\":\"cancel\"}]"], ["valueVariableOptions", [{
                                            "key": "$system_queue_time",
                                            "name": "Caller's waiting time in queue",
                                            "type": "globalvar"
                                        }, {
                                            "key": "$ciq_destination",
                                            "name": "Caller's number",
                                            "type": "globalvar"
                                        }, {
                                            "key": "$system_queue_place",
                                            "name": "Current place in queue",
                                            "type": "globalvar"
                                        }, {
                                            "key": "$system_queue_estimate",
                                            "name": "Estimated time remaing in queue",
                                            "type": "globalvar"
                                        }, {
                                            "key": "$system_secret_caller",
                                            "name": "Caller has a secret number",
                                            "type": "globalvar"
                                        }, {
                                            "key": "$system_accessno",
                                            "name": "The number of this service",
                                            "type": "globalvar"
                                        }
                                    ]], ["areInterruptExitsDuplicate", false], ["queueInfoList", ["__CALLOUT_FROM_SMS", "__CALLOUT_JAN", "__CALLOUT_NTS", "__recordingControl", "broadcast", "chat_sales", "chat_support", "chat_test", "dfafd", "dfasdsss", "hot_stand_by", "Q_EMAIL_SALES", "Q_EMAIL_SUPPORT", "Q_P_JAN_SALES", "Q_P_JAN_SUPPORT", "Q_PERSONAL", "Q_SMS2IVR", "Q_TACO", "QFacebook", "QFacebookPrivate", "QFacebookPublic", "testaaa"]]],
                            "moduleId": "queue1",
                            "moduleName": "Основна опашка",
                            "isSelected": true
                        }
                    ], ["Messages", {
                            "tabName": "Messages",
                            "moduleType": "queue",
                            "propertyValues": [["name", "Основна опашка"], ["entertainer", "No custom entertainer!"], ["hascustomentertainer", false]],
                            "moduleId": "queue1",
                            "moduleName": "Основна опашка",
                            "isSelected": false
                        }
                    ], ["Advanced", {
                            "tabName": "Advanced",
                            "moduleType": "queue",
                            "propertyValues": [["ct_label", "Основна опашка"]],
                            "moduleId": "queue1",
                            "moduleName": "Основна опашка",
                            "isSelected": false
                        }
                    ]],
                "isValid": false
            }, {
                "exits": [{
                        "tag_name": "cancel",
                        "type": "cancel",
                        "sourceEndPoints": [{
                                "endPointType": "s2",
                                "params": [0, 0.5, -1, 0, 0, 0, "left"]
                            }, {
                                "endPointType": "s3",
                                "params": [1, 0.5, 1, 0, 0, 0, "right"]
                            }
                        ],
                        "text": "cancel",
                        "exitDefaultTarget": "terminate",
                        "moduleId": "queue3",
                        "id": "-948696766_-1367724422_queue3_cancel",
                        "next": {
                            "targetId": "terminate",
                            "target": "1",
                            "source": "s3"
                        }
                    }
                ],
                "tabs": [["Basic", {
                            "tabName": "Basic",
                            "moduleType": "queue",
                            "propertyValues": [["name", "Дежурен"], ["queue_key", "q_onduty"], ["hascustomentertainer", "false"], ["exitsJson", "[{\"type\":\"cancel\",\"text\":\"cancel\"}]"], ["valueVariableOptions", [{
                                            "key": "$system_queue_time",
                                            "name": "Caller's waiting time in queue",
                                            "type": "globalvar"
                                        }, {
                                            "key": "$ciq_destination",
                                            "name": "Caller's number",
                                            "type": "globalvar"
                                        }, {
                                            "key": "$system_queue_place",
                                            "name": "Current place in queue",
                                            "type": "globalvar"
                                        }, {
                                            "key": "$system_queue_estimate",
                                            "name": "Estimated time remaing in queue",
                                            "type": "globalvar"
                                        }, {
                                            "key": "$system_secret_caller",
                                            "name": "Caller has a secret number",
                                            "type": "globalvar"
                                        }, {
                                            "key": "$system_accessno",
                                            "name": "The number of this service",
                                            "type": "globalvar"
                                        }
                                    ]], ["areInterruptExitsDuplicate", false], ["queueInfoList", ["__CALLOUT_FROM_SMS", "__CALLOUT_JAN", "__CALLOUT_NTS", "__recordingControl", "broadcast", "chat_sales", "chat_support", "chat_test", "dfafd", "dfasdsss", "hot_stand_by", "Q_EMAIL_SALES", "Q_EMAIL_SUPPORT", "Q_P_JAN_SALES", "Q_P_JAN_SUPPORT", "Q_PERSONAL", "Q_SMS2IVR", "Q_TACO", "QFacebook", "QFacebookPrivate", "QFacebookPublic", "testaaa"]]],
                            "moduleId": "queue3",
                            "moduleName": "Дежурен",
                            "isSelected": true
                        }
                    ], ["Messages", {
                            "tabName": "Messages",
                            "moduleType": "queue",
                            "propertyValues": [["name", "Дежурен"], ["entertainer", "No custom entertainer!"], ["hascustomentertainer", false]],
                            "moduleId": "queue3",
                            "moduleName": "Дежурен",
                            "isSelected": false
                        }
                    ], ["Advanced", {
                            "tabName": "Advanced",
                            "moduleType": "queue",
                            "propertyValues": [["ct_label", "Дежурен"]],
                            "moduleId": "queue3",
                            "moduleName": "Дежурен",
                            "isSelected": false
                        }
                    ]],
                "isValid": false
            }, {
                "exits": [{
                        "_DEFAULT_SOURCE_ANCHOR": "s4",
                        "type": "default",
                        "sourceEndPoints": [{
                                "endPointType": "s2",
                                "params": [0, 0.5, -1, 0, 0, 0, "left"]
                            }, {
                                "endPointType": "s3",
                                "params": [1, 0.5, 1, 0, 0, 0, "right"]
                            }
                        ],
                        "text": "default",
                        "exitDefaultTarget": "terminate",
                        "moduleId": "audio6",
                        "id": "-1406804192_1544803905_audio6_default",
                        "next": {
                            "targetId": "queue1",
                            "target": "2",
                            "source": "s3"
                        },
                        "_isVisible": false
                    }
                ],
                "tabs": [["Basic", {
                            "tabName": "Basic",
                            "moduleType": "audio",
                            "propertyValues": [["name", "Welcome_"], ["src", "/500187/ControlAudio/Welcome.wav"]],
                            "moduleId": "audio6",
                            "moduleName": "Welcome_",
                            "isSelected": true
                        }
                    ], ["Advanced", {
                            "tabName": "Advanced",
                            "moduleType": "audio",
                            "propertyValues": [["format", null], ["timeout", null], ["conid", ""], ["ct_label", null], ["cc_label", "Welcome_"]],
                            "moduleId": "audio6",
                            "moduleName": "Welcome_",
                            "isSelected": false
                        }
                    ]],
                "isValid": true
            }
        ]]]
